{
  "textures": {
    "0": "minescape/entities/queen-land",
    "particle": "minescape/entities/queen-land"
  },
  "elements": [
    {
      "from": [
        0.7518247222222243,
        -4.910630333333334,
        6.929503333333336
      ],
      "to": [
        2.9080747222222243,
        0.005619666666666134,
        9.517003333333333
      ],
      "rotation": {
        "angle": -22.5,
        "axis": "z",
        "origin": [
          2.1318247222222233,
          -2.5818803333333324,
          9.085753333333333
        ]
      },
      "faces": {
        "north": {
          "uv": [
            8.5,
            7.25,
            8.75,
            7.5
          ],
          "texture": "#0"
        },
        "east": {
          "uv": [
            8.5,
            7.5,
            8.75,
            7.75
          ],
          "texture": "#0"
        },
        "south": {
          "uv": [
            8.5,
            7.75,
            8.75,
            8
          ],
          "texture": "#0"
        },
        "west": {
          "uv": [
            8.5,
            8,
            8.75,
            8.25
          ],
          "texture": "#0"
        },
        "up": {
          "uv": [
            8.75,
            8.5,
            8.5,
            8.25
          ],
          "texture": "#0"
        },
        "down": {
          "uv": [
            0.25,
            8.75,
            0,
            9
          ],
          "texture": "#0"
        }
      }
    },
    {
      "from": [
        0.4073537222222221,
        -10.613089333333333,
        7.360753333333336
      ],
      "to": [
        1.3561037222222225,
        -3.195612333333333,
        9.085753333333335
      ],
      "rotation": {
        "angle": 0,
        "axis": "y",
        "origin": [
          1.787353722222221,
          -5.438089333333333,
          8.654503333333333
        ]
      },
      "faces": {
        "north": {
          "uv": [
            0.25,
            7.25,
            0.5,
            7.75
          ],
          "texture": "#0"
        },
        "east": {
          "uv": [
            1,
            7.25,
            1.25,
            7.75
          ],
          "texture": "#0"
        },
        "south": {
          "uv": [
            1.25,
            7.25,
            1.5,
            7.75
          ],
          "texture": "#0"
        },
        "west": {
          "uv": [
            1.5,
            7.25,
            1.75,
            7.75
          ],
          "texture": "#0"
        },
        "up": {
          "uv": [
            0.5,
            9,
            0.25,
            8.75
          ],
          "texture": "#0"
        },
        "down": {
          "uv": [
            0.75,
            8.75,
            0.5,
            9
          ],
          "texture": "#0"
        }
      }
    },
    {
      "from": [
        2.1086637222222215,
        1.6889896666666662,
        6.929503333333336
      ],
      "to": [
        11.59618672222222,
        4.017739666666666,
        9.517003333333333
      ],
      "rotation": {
        "angle": 45,
        "axis": "z",
        "origin": [
          6.42118672222222,
          1.8614896666666656,
          9.085753333333333
        ]
      },
      "faces": {
        "north": {
          "uv": [
            6,
            2,
            6.75,
            2.25
          ],
          "texture": "#0"
        },
        "east": {
          "uv": [
            8.5,
            6.75,
            8.75,
            7
          ],
          "texture": "#0"
        },
        "south": {
          "uv": [
            6,
            2.25,
            6.75,
            2.5
          ],
          "texture": "#0"
        },
        "west": {
          "uv": [
            8.5,
            7,
            8.75,
            7.25
          ],
          "texture": "#0"
        },
        "up": {
          "uv": [
            6.75,
            2.75,
            6,
            2.5
          ],
          "texture": "#0"
        },
        "down": {
          "uv": [
            6.75,
            3.25,
            6,
            3.5
          ],
          "texture": "#0"
        }
      }
    },
    {
      "from": [
        5.558663722222221,
        1.3439896666666673,
        6.757003333333335
      ],
      "to": [
        9.267413722222221,
        4.448966666666667,
        9.603253333333337
      ],
      "rotation": {
        "angle": 45,
        "axis": "z",
        "origin": [
          6.42118672222222,
          1.8614896666666656,
          9.085753333333333
        ]
      },
      "faces": {
        "north": {
          "uv": [
            5.25,
            8.75,
            5.5,
            9
          ],
          "texture": "#0"
        },
        "east": {
          "uv": [
            5.5,
            8.75,
            5.75,
            9
          ],
          "texture": "#0"
        },
        "south": {
          "uv": [
            5.75,
            8.75,
            6,
            9
          ],
          "texture": "#0"
        },
        "west": {
          "uv": [
            6,
            8.75,
            6.25,
            9
          ],
          "texture": "#0"
        },
        "up": {
          "uv": [
            6.5,
            9,
            6.25,
            8.75
          ],
          "texture": "#0"
        },
        "down": {
          "uv": [
            6.75,
            8.75,
            6.5,
            9
          ],
          "texture": "#0"
        }
      }
    },
    {
      "from": [
        7.838676722222221,
        -0.6083653333333352,
        6.608791333333334
      ],
      "to": [
        11.633676722222221,
        7.240384666666666,
        9.800041333333334
      ],
      "rotation": {
        "angle": 22.5,
        "axis": "z",
        "origin": [
          9.908676722222221,
          2.4103846666666655,
          7.385041333333335
        ]
      },
      "faces": {
        "north": {
          "uv": [
            4.25,
            7.25,
            4.5,
            7.75
          ],
          "texture": "#0"
        },
        "east": {
          "uv": [
            4.5,
            7.25,
            4.75,
            7.75
          ],
          "texture": "#0"
        },
        "south": {
          "uv": [
            4.75,
            7.25,
            5,
            7.75
          ],
          "texture": "#0"
        },
        "west": {
          "uv": [
            5,
            7.25,
            5.25,
            7.75
          ],
          "texture": "#0"
        },
        "up": {
          "uv": [
            4,
            9,
            3.75,
            8.75
          ],
          "texture": "#0"
        },
        "down": {
          "uv": [
            4.25,
            8.75,
            4,
            9
          ],
          "texture": "#0"
        }
      }
    },
    {
      "from": [
        10.136652722222221,
        -4.920888333333333,
        4.711291333333336
      ],
      "to": [
        22.21165272222222,
        -1.3846153333333326,
        9.023791333333333
      ],
      "rotation": {
        "angle": 22.5,
        "axis": "y",
        "origin": [
          14.449152722222221,
          -2.7646153333333334,
          6.867541333333336
        ]
      },
      "faces": {
        "north": {
          "uv": [
            5,
            1.75,
            6,
            2
          ],
          "texture": "#0"
        },
        "east": {
          "uv": [
            8.5,
            2.75,
            8.75,
            3
          ],
          "texture": "#0"
        },
        "south": {
          "uv": [
            5,
            2,
            6,
            2.25
          ],
          "texture": "#0"
        },
        "west": {
          "uv": [
            8.5,
            3,
            8.75,
            3.25
          ],
          "texture": "#0"
        },
        "up": {
          "uv": [
            6,
            2.5,
            5,
            2.25
          ],
          "texture": "#0"
        },
        "down": {
          "uv": [
            6,
            2.5,
            5,
            2.75
          ],
          "texture": "#0"
        }
      }
    },
    {
      "from": [
        8.183676722222222,
        -3.6271153333333332,
        6.929503333333336
      ],
      "to": [
        11.288676722222222,
        4.997884666666667,
        9.517003333333333
      ],
      "rotation": {
        "angle": 22.5,
        "axis": "z",
        "origin": [
          9.908676722222221,
          2.4103846666666655,
          9.085753333333333
        ]
      },
      "faces": {
        "north": {
          "uv": [
            7,
            4,
            7.25,
            4.5
          ],
          "texture": "#0"
        },
        "east": {
          "uv": [
            7,
            5.25,
            7.25,
            5.75
          ],
          "texture": "#0"
        },
        "south": {
          "uv": [
            7,
            5.75,
            7.25,
            6.25
          ],
          "texture": "#0"
        },
        "west": {
          "uv": [
            0,
            7.25,
            0.25,
            7.75
          ],
          "texture": "#0"
        },
        "up": {
          "uv": [
            8.75,
            6.5,
            8.5,
            6.25
          ],
          "texture": "#0"
        },
        "down": {
          "uv": [
            8.75,
            6.5,
            8.5,
            6.75
          ],
          "texture": "#0"
        }
      }
    },
    {
      "from": [
        5.731186722222223,
        4.362716666666666,
        7.360753333333336
      ],
      "to": [
        8.318686722222223,
        6.863989666666667,
        8.482003333333335
      ],
      "rotation": {
        "angle": 0,
        "axis": "y",
        "origin": [
          8.05991372222222,
          6.518966666666666,
          8.482003333333335
        ]
      },
      "faces": {
        "north": {
          "uv": [
            2.5,
            9.5,
            2.75,
            9.75
          ],
          "texture": "#0"
        },
        "east": {
          "uv": [
            2.75,
            9.5,
            3,
            9.75
          ],
          "texture": "#0"
        },
        "south": {
          "uv": [
            3,
            9.5,
            3.25,
            9.75
          ],
          "texture": "#0"
        },
        "west": {
          "uv": [
            3.25,
            9.5,
            3.5,
            9.75
          ],
          "texture": "#0"
        },
        "up": {
          "uv": [
            3.75,
            9.75,
            3.5,
            9.5
          ],
          "texture": "#0"
        },
        "down": {
          "uv": [
            4,
            9.5,
            3.75,
            9.75
          ],
          "texture": "#0"
        }
      }
    }
  ],
  "name": "leg5",
  "display": {
    "head": {
      "translation": [
        -17.40565888888888,
        43.41992933333333,
        0.26591066666665597
      ],
      "scale": [
        4,
        4,
        4
      ]
    },
    "thirdperson_righthand": {
      "translation": [
        12.662088194444445,
        -2.16619416666666,
        37.137455833333334
      ],
      "rotation": [
        90,
        0,
        0
      ],
      "scale": [
        2.5,
        2.5,
        2.5
      ]
    },
    "thirdperson_lefthand": {
      "translation": [
        34.41916180555555,
        -2.16619416666666,
        37.137455833333334
      ],
      "rotation": [
        90,
        0,
        0
      ],
      "scale": [
        2.5,
        2.5,
        2.5
      ]
    },
    "gui": {
      "rotation": [
        25,
        135,
        0
      ],
      "scale": [
        0.6956521739130436,
        0.6956521739130436,
        0.6956521739130436
      ]
    }
  }
}