{
  "textures": {
    "0": "minescape/entities/black-demon",
    "particle": "minescape/entities/black-demon"
  },
  "elements": [
    {
      "from": [
        5.3851113124999905,
        9.1781916875,
        3.549455437499999
      ],
      "to": [
        10.560111312499991,
        17.8031916875,
        10.4494554375
      ],
      "rotation": {
        "angle": -22.5,
        "axis": "x",
        "origin": [
          6.535111312499993,
          14.9281916875,
          6.999455437499999
        ]
      },
      "faces": {
        "north": {
          "uv": [
            8.75,
            6.75,
            9.25,
            7.25
          ],
          "texture": "#0"
        },
        "east": {
          "uv": [
            7.75,
            0.5,
            8.5,
            1
          ],
          "texture": "#0"
        },
        "south": {
          "uv": [
            9,
            0.5,
            9.5,
            1
          ],
          "texture": "#0"
        },
        "west": {
          "uv": [
            7.75,
            1.75,
            8.5,
            2.25
          ],
          "texture": "#0"
        },
        "up": {
          "uv": [
            8.25,
            4.25,
            7.75,
            3.5
          ],
          "texture": "#0"
        },
        "down": {
          "uv": [
            8.25,
            4.25,
            7.75,
            5
          ],
          "texture": "#0"
        }
      }
    },
    {
      "from": [
        5.3851113124999905,
        5.153191687499998,
        4.124455437499999
      ],
      "to": [
        9.985111312499992,
        9.1781916875,
        9.8744554375
      ],
      "rotation": {
        "angle": -22.5,
        "axis": "x",
        "origin": [
          6.535111312499993,
          14.9281916875,
          6.999455437499999
        ]
      },
      "faces": {
        "north": {
          "uv": [
            9,
            2.75,
            9.5,
            3.25
          ],
          "texture": "#0"
        },
        "east": {
          "uv": [
            7.75,
            5,
            8.5,
            5.5
          ],
          "texture": "#0"
        },
        "south": {
          "uv": [
            9,
            3.75,
            9.5,
            4.25
          ],
          "texture": "#0"
        },
        "west": {
          "uv": [
            7.75,
            5.5,
            8.5,
            6
          ],
          "texture": "#0"
        },
        "up": {
          "uv": [
            3.5,
            8.75,
            3,
            8
          ],
          "texture": "#0"
        },
        "down": {
          "uv": [
            7,
            8,
            6.5,
            8.75
          ],
          "texture": "#0"
        }
      }
    },
    {
      "from": [
        5.730111312499993,
        -3.471808312500002,
        7.1144554375
      ],
      "to": [
        9.755111312499992,
        8.028191687499994,
        12.289455437500001
      ],
      "rotation": {
        "angle": 22.5,
        "axis": "x",
        "origin": [
          6.880111312499995,
          5.728191687499997,
          9.414455437500001
        ]
      },
      "faces": {
        "north": {
          "uv": [
            1,
            5.75,
            1.5,
            7
          ],
          "texture": "#0"
        },
        "east": {
          "uv": [
            1.5,
            5.75,
            2,
            7
          ],
          "texture": "#0"
        },
        "south": {
          "uv": [
            2,
            5.75,
            2.5,
            7
          ],
          "texture": "#0"
        },
        "west": {
          "uv": [
            2.5,
            5.75,
            3,
            7
          ],
          "texture": "#0"
        },
        "up": {
          "uv": [
            9.5,
            6.5,
            9,
            6
          ],
          "texture": "#0"
        },
        "down": {
          "uv": [
            9.5,
            8,
            9,
            8.5
          ],
          "texture": "#0"
        }
      }
    },
    {
      "from": [
        8.030111312499994,
        -8.0718083125,
        6.539455437500001
      ],
      "to": [
        10.330111312499994,
        -3.471808312500002,
        8.8394554375
      ],
      "rotation": {
        "angle": 22.5,
        "axis": "x",
        "origin": [
          6.880111312499995,
          5.728191687499997,
          9.414455437500001
        ]
      },
      "faces": {
        "north": {
          "uv": [
            10.25,
            1,
            10.5,
            1.5
          ],
          "texture": "#0"
        },
        "east": {
          "uv": [
            10.25,
            1.5,
            10.5,
            2
          ],
          "texture": "#0"
        },
        "south": {
          "uv": [
            10.25,
            2,
            10.5,
            2.5
          ],
          "texture": "#0"
        },
        "west": {
          "uv": [
            10.25,
            2.5,
            10.5,
            3
          ],
          "texture": "#0"
        },
        "up": {
          "uv": [
            12,
            11.25,
            11.75,
            11
          ],
          "texture": "#0"
        },
        "down": {
          "uv": [
            12,
            11.25,
            11.75,
            11.5
          ],
          "texture": "#0"
        }
      }
    },
    {
      "from": [
        8.030111312499994,
        -9.279308312500001,
        9.4719554375
      ],
      "to": [
        10.330111312499994,
        -4.679308312500002,
        11.7719554375
      ],
      "rotation": {
        "angle": 22.5,
        "axis": "x",
        "origin": [
          6.880111312499995,
          4.520691687500001,
          12.346955437500002
        ]
      },
      "faces": {
        "north": {
          "uv": [
            10.25,
            3,
            10.5,
            3.5
          ],
          "texture": "#0"
        },
        "east": {
          "uv": [
            10.25,
            3.5,
            10.5,
            4
          ],
          "texture": "#0"
        },
        "south": {
          "uv": [
            10.25,
            4,
            10.5,
            4.5
          ],
          "texture": "#0"
        },
        "west": {
          "uv": [
            10.25,
            5,
            10.5,
            5.5
          ],
          "texture": "#0"
        },
        "up": {
          "uv": [
            12,
            11.75,
            11.75,
            11.5
          ],
          "texture": "#0"
        },
        "down": {
          "uv": [
            0.25,
            12,
            0,
            12.25
          ],
          "texture": "#0"
        }
      }
    },
    {
      "from": [
        7.570111312499993,
        -9.293108312500001,
        4.779219437500001
      ],
      "to": [
        9.295111312499994,
        -6.418108312499999,
        6.7342194375
      ],
      "rotation": {
        "angle": -22.5,
        "axis": "z",
        "origin": [
          8.432611312499997,
          -7.855608312500003,
          5.7567194375
        ]
      },
      "faces": {
        "north": {
          "uv": [
            0.25,
            12,
            0.5,
            12.25
          ],
          "texture": "#0"
        },
        "east": {
          "uv": [
            0.5,
            12,
            0.75,
            12.25
          ],
          "texture": "#0"
        },
        "south": {
          "uv": [
            0.75,
            12,
            1,
            12.25
          ],
          "texture": "#0"
        },
        "west": {
          "uv": [
            1,
            12,
            1.25,
            12.25
          ],
          "texture": "#0"
        },
        "up": {
          "uv": [
            1.5,
            12.25,
            1.25,
            12
          ],
          "texture": "#0"
        },
        "down": {
          "uv": [
            1.75,
            12,
            1.5,
            12.25
          ],
          "texture": "#0"
        }
      }
    },
    {
      "from": [
        8.145111312499996,
        -9.408108312500001,
        2.0192194375000003
      ],
      "to": [
        8.720111312499995,
        -7.6831083125,
        3.3992194374999993
      ],
      "rotation": {
        "angle": -22.5,
        "axis": "z",
        "origin": [
          8.432611312499997,
          -7.970608312500001,
          2.9967194375000004
        ]
      },
      "faces": {
        "north": {
          "uv": [
            1.75,
            12,
            2,
            12.25
          ],
          "texture": "#0"
        },
        "east": {
          "uv": [
            2,
            12,
            2.25,
            12.25
          ],
          "texture": "#0"
        },
        "south": {
          "uv": [
            2.25,
            12,
            2.5,
            12.25
          ],
          "texture": "#0"
        },
        "west": {
          "uv": [
            2.5,
            12,
            2.75,
            12.25
          ],
          "texture": "#0"
        },
        "up": {
          "uv": [
            3,
            12.25,
            2.75,
            12
          ],
          "texture": "#0"
        },
        "down": {
          "uv": [
            3.25,
            12,
            3,
            12.25
          ],
          "texture": "#0"
        }
      }
    },
    {
      "from": [
        8.145111312499996,
        -10.5581083125,
        4.8942194375
      ],
      "to": [
        8.720111312499995,
        -8.8331083125,
        6.274219437499999
      ],
      "rotation": {
        "angle": -22.5,
        "axis": "z",
        "origin": [
          8.432611312499997,
          -9.120608312500002,
          5.8717194375
        ]
      },
      "faces": {
        "north": {
          "uv": [
            3.25,
            12,
            3.5,
            12.25
          ],
          "texture": "#0"
        },
        "east": {
          "uv": [
            3.5,
            12,
            3.75,
            12.25
          ],
          "texture": "#0"
        },
        "south": {
          "uv": [
            3.75,
            12,
            4,
            12.25
          ],
          "texture": "#0"
        },
        "west": {
          "uv": [
            4,
            12,
            4.25,
            12.25
          ],
          "texture": "#0"
        },
        "up": {
          "uv": [
            4.5,
            12.25,
            4.25,
            12
          ],
          "texture": "#0"
        },
        "down": {
          "uv": [
            4.75,
            12,
            4.5,
            12.25
          ],
          "texture": "#0"
        }
      }
    },
    {
      "from": [
        5.270111312499996,
        -7.223108312499999,
        2.8242194375
      ],
      "to": [
        5.845111312499995,
        -5.498108312500001,
        4.204219437500001
      ],
      "rotation": {
        "angle": 22.5,
        "axis": "z",
        "origin": [
          6.132611312499993,
          -5.785608312500003,
          3.801719437499999
        ]
      },
      "faces": {
        "north": {
          "uv": [
            4.75,
            12,
            5,
            12.25
          ],
          "texture": "#0"
        },
        "east": {
          "uv": [
            5,
            12,
            5.25,
            12.25
          ],
          "texture": "#0"
        },
        "south": {
          "uv": [
            5.25,
            12,
            5.5,
            12.25
          ],
          "texture": "#0"
        },
        "west": {
          "uv": [
            5.5,
            12,
            5.75,
            12.25
          ],
          "texture": "#0"
        },
        "up": {
          "uv": [
            6,
            12.25,
            5.75,
            12
          ],
          "texture": "#0"
        },
        "down": {
          "uv": [
            6.25,
            12,
            6,
            12.25
          ],
          "texture": "#0"
        }
      }
    },
    {
      "from": [
        7.570111312499993,
        -8.2581083125,
        1.7892194375
      ],
      "to": [
        9.295111312499994,
        -5.383108312499999,
        3.744219437500001
      ],
      "rotation": {
        "angle": -22.5,
        "axis": "z",
        "origin": [
          8.432611312499997,
          -6.820608312500003,
          2.766719437500001
        ]
      },
      "faces": {
        "north": {
          "uv": [
            6.25,
            12,
            6.5,
            12.25
          ],
          "texture": "#0"
        },
        "east": {
          "uv": [
            6.5,
            12,
            6.75,
            12.25
          ],
          "texture": "#0"
        },
        "south": {
          "uv": [
            6.75,
            12,
            7,
            12.25
          ],
          "texture": "#0"
        },
        "west": {
          "uv": [
            7,
            12,
            7.25,
            12.25
          ],
          "texture": "#0"
        },
        "up": {
          "uv": [
            7.5,
            12.25,
            7.25,
            12
          ],
          "texture": "#0"
        },
        "down": {
          "uv": [
            7.75,
            12,
            7.5,
            12.25
          ],
          "texture": "#0"
        }
      }
    },
    {
      "from": [
        5.155111312499994,
        -5.369308312499999,
        7.2869554375
      ],
      "to": [
        6.880111312499995,
        -2.4943083124999994,
        9.586955437499999
      ],
      "rotation": {
        "angle": 22.5,
        "axis": "x",
        "origin": [
          4.005111312499995,
          6.130691687499997,
          7.861955437499999
        ]
      },
      "faces": {
        "north": {
          "uv": [
            7.75,
            12,
            8,
            12.25
          ],
          "texture": "#0"
        },
        "east": {
          "uv": [
            8,
            12,
            8.25,
            12.25
          ],
          "texture": "#0"
        },
        "south": {
          "uv": [
            8.25,
            12,
            8.5,
            12.25
          ],
          "texture": "#0"
        },
        "west": {
          "uv": [
            8.5,
            12,
            8.75,
            12.25
          ],
          "texture": "#0"
        },
        "up": {
          "uv": [
            9,
            12.25,
            8.75,
            12
          ],
          "texture": "#0"
        },
        "down": {
          "uv": [
            9.25,
            12,
            9,
            12.25
          ],
          "texture": "#0"
        }
      }
    },
    {
      "from": [
        5.212611312499995,
        -6.921808312500001,
        6.826955437500001
      ],
      "to": [
        6.765111312499997,
        -4.046808312500005,
        8.724455437499998
      ],
      "rotation": {
        "angle": 22.5,
        "axis": "x",
        "origin": [
          4.062611312499994,
          4.578191687499999,
          7.401955437500001
        ]
      },
      "faces": {
        "north": {
          "uv": [
            9.25,
            12,
            9.5,
            12.25
          ],
          "texture": "#0"
        },
        "east": {
          "uv": [
            9.5,
            12,
            9.75,
            12.25
          ],
          "texture": "#0"
        },
        "south": {
          "uv": [
            9.75,
            12,
            10,
            12.25
          ],
          "texture": "#0"
        },
        "west": {
          "uv": [
            10,
            12,
            10.25,
            12.25
          ],
          "texture": "#0"
        },
        "up": {
          "uv": [
            10.5,
            12.25,
            10.25,
            12
          ],
          "texture": "#0"
        },
        "down": {
          "uv": [
            10.75,
            12,
            10.5,
            12.25
          ],
          "texture": "#0"
        }
      }
    },
    {
      "from": [
        8.662611312499994,
        7.0395366874999965,
        12.339250437499999
      ],
      "to": [
        9.812611312499993,
        8.764536687499994,
        14.064250437499998
      ],
      "rotation": {
        "angle": -22.5,
        "axis": "y",
        "origin": [
          9.237611312499997,
          7.902036687499997,
          12.914250437499998
        ]
      },
      "faces": {
        "north": {
          "uv": [
            10.75,
            12,
            11,
            12.25
          ],
          "texture": "#0"
        },
        "east": {
          "uv": [
            11,
            12,
            11.25,
            12.25
          ],
          "texture": "#0"
        },
        "south": {
          "uv": [
            11.25,
            12,
            11.5,
            12.25
          ],
          "texture": "#0"
        },
        "west": {
          "uv": [
            11.5,
            12,
            11.75,
            12.25
          ],
          "texture": "#0"
        },
        "up": {
          "uv": [
            12,
            12.25,
            11.75,
            12
          ],
          "texture": "#0"
        },
        "down": {
          "uv": [
            12.25,
            12,
            12,
            12.25
          ],
          "texture": "#0"
        }
      }
    },
    {
      "from": [
        8.835111312499993,
        7.2695366875000005,
        14.064250437499998
      ],
      "to": [
        9.697611312499994,
        8.534536687499997,
        15.214250437499999
      ],
      "rotation": {
        "angle": -45,
        "axis": "y",
        "origin": [
          9.467611312499994,
          7.902036687499997,
          13.489250437499999
        ]
      },
      "faces": {
        "north": {
          "uv": [
            12,
            0,
            12.25,
            0.25
          ],
          "texture": "#0"
        },
        "east": {
          "uv": [
            12,
            0.25,
            12.25,
            0.5
          ],
          "texture": "#0"
        },
        "south": {
          "uv": [
            12,
            0.5,
            12.25,
            0.75
          ],
          "texture": "#0"
        },
        "west": {
          "uv": [
            12,
            0.75,
            12.25,
            1
          ],
          "texture": "#0"
        },
        "up": {
          "uv": [
            12.25,
            1.25,
            12,
            1
          ],
          "texture": "#0"
        },
        "down": {
          "uv": [
            12.25,
            1.25,
            12,
            1.5
          ],
          "texture": "#0"
        }
      }
    },
    {
      "from": [
        7.133502312499996,
        7.557036687499998,
        14.0702994375
      ],
      "to": [
        8.283502312499994,
        8.247036687499996,
        14.357799437499999
      ],
      "rotation": {
        "angle": 45,
        "axis": "y",
        "origin": [
          8.571002312499996,
          7.902036687499997,
          14.214049437499998
        ]
      },
      "faces": {
        "north": {
          "uv": [
            12,
            1.5,
            12.25,
            1.75
          ],
          "texture": "#0"
        },
        "east": {
          "uv": [
            12,
            1.75,
            12.25,
            2
          ],
          "texture": "#0"
        },
        "south": {
          "uv": [
            12,
            2,
            12.25,
            2.25
          ],
          "texture": "#0"
        },
        "west": {
          "uv": [
            12,
            2.25,
            12.25,
            2.5
          ],
          "texture": "#0"
        },
        "up": {
          "uv": [
            12.25,
            2.75,
            12,
            2.5
          ],
          "texture": "#0"
        },
        "down": {
          "uv": [
            12.25,
            2.75,
            12,
            3
          ],
          "texture": "#0"
        }
      }
    }
  ],
  "name": "arm2",
  "display": {
    "head": {
      "translation": [
        -1.1782719374999953,
        -10.94651384510869,
        0.9830506874999995
      ],
      "scale": [
        1.6086956521739133,
        1.6086956521739133,
        1.6086956521739133
      ]
    },
    "thirdperson_righthand": {
      "translation": [
        4.826080039062503,
        -2.6144066796875,
        3.1584288468070696
      ],
      "rotation": [
        90,
        0,
        0
      ],
      "scale": [
        1.0054347826086958,
        1.0054347826086958,
        1.0054347826086958
      ]
    },
    "thirdperson_lefthand": {
      "translation": [
        6.298919960937497,
        -2.6144066796875,
        3.1584288468070696
      ],
      "rotation": [
        90,
        0,
        0
      ],
      "scale": [
        1.0054347826086958,
        1.0054347826086958,
        1.0054347826086958
      ]
    },
    "gui": {
      "rotation": [
        25,
        135,
        0
      ],
      "scale": [
        0.6956521739130436,
        0.6956521739130436,
        0.6956521739130436
      ]
    }
  }
}