{
	"__comment": "Designed by Scipio3000 with Cubik Studio - https://cubik.studio",
	"textures": {
		"0": "minescape/entities/black-demon",
		"particle": "minescape/entities/black-demon"
	},
	"elements": [ 	 
		{
			"__comment": "Element",
			"from": [ 7.0428, -7.7218, -14.823 ],
			"to": [ 8.6528, -5.0768, -4.818 ],
			"rotation": { "origin": [ 8.192831, -6.226799, -12.523 ], "axis": "x", "angle": -22.5 },
			"faces": {
				"down": { "uv": [ 3.75, 9.25, 3.5, 10.25 ], "texture": "#0" },
				"up": { "uv": [ 3.5, 10.25, 3.25, 9.25 ], "texture": "#0" },
				"north": { "uv": [ 12, 3, 12.25, 3.25 ], "texture": "#0" },
				"south": { "uv": [ 12, 3.25, 12.25, 3.5 ], "texture": "#0" },
				"west": { "uv": [ 9, 3.25, 10, 3.5 ], "texture": "#0" },
				"east": { "uv": [ 8.75, 8.5, 9.75, 8.75 ], "texture": "#0" }
			}
		},
		{
			"__comment": "Element",
			"from": [ 7.8478, -4.3868, -5.393 ],
			"to": [ 8.1353, -3.236799, 1.7945 ],
			"rotation": { "origin": [ 7.991581, -3.668049, -3.380501 ], "axis": "x", "angle": 45 },
			"faces": {
				"down": { "uv": [ 4.5, 9.75, 4.25, 10.5 ], "texture": "#0" },
				"up": { "uv": [ 3, 10.5, 2.75, 9.75 ], "texture": "#0" },
				"north": { "uv": [ 12, 5, 12.25, 5.25 ], "texture": "#0" },
				"south": { "uv": [ 12, 5.25, 12.25, 5.5 ], "texture": "#0" },
				"west": { "uv": [ 9.5, 9.25, 10.25, 9.5 ], "texture": "#0" },
				"east": { "uv": [ 9.5, 8.25, 10.25, 8.5 ], "texture": "#0" }
			}
		},
		{
			"__comment": "Element",
			"from": [ 7.8478, -5.3643, -6.083 ],
			"to": [ 8.1353, -3.0068, -3.8405 ],
			"faces": {
				"down": { "uv": [ 12.25, 6.75, 12, 7 ], "texture": "#0" },
				"up": { "uv": [ 12.25, 6.75, 12, 6.5 ], "texture": "#0" },
				"north": { "uv": [ 12, 5.5, 12.25, 5.75 ], "texture": "#0" },
				"south": { "uv": [ 12, 6, 12.25, 6.25 ], "texture": "#0" },
				"west": { "uv": [ 12, 6.25, 12.25, 6.5 ], "texture": "#0" },
				"east": { "uv": [ 12, 5.75, 12.25, 6 ], "texture": "#0" }
			}
		},
		{
			"__comment": "Element",
			"from": [ 7.8478, -5.8243, -3.783 ],
			"to": [ 8.1353, -4.616799, -1.5405 ],
			"rotation": { "origin": [ 7.991581, -4.128048, -2.575501 ], "axis": "x", "angle": 22.5 },
			"faces": {
				"down": { "uv": [ 12.25, 8.25, 12, 8.5 ], "texture": "#0" },
				"up": { "uv": [ 12.25, 8.25, 12, 8 ], "texture": "#0" },
				"north": { "uv": [ 12, 7, 12.25, 7.25 ], "texture": "#0" },
				"south": { "uv": [ 12, 7.5, 12.25, 7.75 ], "texture": "#0" },
				"west": { "uv": [ 12, 7.75, 12.25, 8 ], "texture": "#0" },
				"east": { "uv": [ 12, 7.25, 12.25, 7.5 ], "texture": "#0" }
			}
		},
		{
			"__comment": "Element",
			"from": [ 7.8478, -8.5186, -8.440599 ],
			"to": [ 8.1353, -7.081097, 2.886901 ],
			"rotation": { "origin": [ 7.991581, -7.684884, 0.5869304 ], "axis": "x", "angle": 22.5 },
			"faces": {
				"down": { "uv": [ 2.75, 8.5, 2.5, 9.75 ], "texture": "#0" },
				"up": { "uv": [ 8.5, 4.25, 8.25, 3 ], "texture": "#0" },
				"north": { "uv": [ 12, 8.5, 12.25, 8.75 ], "texture": "#0" },
				"south": { "uv": [ 12, 8.75, 12.25, 9 ], "texture": "#0" },
				"west": { "uv": [ 8.25, 1.5, 9.5, 1.75 ], "texture": "#0" },
				"east": { "uv": [ 8.25, 1.25, 9.5, 1.5 ], "texture": "#0" }
			}
		},
		{
			"__comment": "Element",
			"from": [ 7.8478, -7.4918, -13.6155 ],
			"to": [ 8.1353, -5.0193, -5.910497 ],
			"rotation": { "origin": [ 7.991581, -6.888049, -9.073001 ], "axis": "x", "angle": -45 },
			"faces": {
				"down": { "uv": [ 5.75, 9.75, 5.5, 10.5 ], "texture": "#0" },
				"up": { "uv": [ 5.5, 10.5, 5.25, 9.75 ], "texture": "#0" },
				"north": { "uv": [ 12, 9, 12.25, 9.25 ], "texture": "#0" },
				"south": { "uv": [ 12, 9.25, 12.25, 9.5 ], "texture": "#0" },
				"west": { "uv": [ 6.5, 9.75, 7.25, 10 ], "texture": "#0" },
				"east": { "uv": [ 4.5, 9.75, 5.25, 10 ], "texture": "#0" }
			}
		},
		{
			"__comment": "Element",
			"from": [ 7.5148, 7.179, 4.7342 ],
			"to": [ 8.664799, 8.329, 14.5092 ],
			"faces": {
				"down": { "uv": [ 9.25, 9.25, 9, 10.25 ], "texture": "#0" },
				"up": { "uv": [ 9, 10.25, 8.75, 9.25 ], "texture": "#0" },
				"north": { "uv": [ 12, 9.5, 12.25, 9.75 ], "texture": "#0" },
				"south": { "uv": [ 12, 9.75, 12.25, 10 ], "texture": "#0" },
				"west": { "uv": [ 7.5, 9.25, 8.5, 9.5 ], "texture": "#0" },
				"east": { "uv": [ 6.5, 9.25, 7.5, 9.5 ], "texture": "#0" }
			}
		},
		{
			"__comment": "Element",
			"from": [ 7.8598, -2.6941, 5.4574 ],
			"to": [ 8.0898, 7.713399, 14.6574 ],
			"faces": {
				"down": { "uv": [ 9.5, 1.75, 9.25, 2.75 ], "texture": "#0" },
				"up": { "uv": [ 9.5, 10.25, 9.25, 9.25 ], "texture": "#0" },
				"north": { "uv": [ 2.75, 8.5, 3, 9.75 ], "texture": "#0" },
				"south": { "uv": [ 4.25, 8.5, 4.5, 9.75 ], "texture": "#0" },
				"west": { "uv": [ 3, 3, 4, 4.25 ], "texture": "#0" },
				"east": { "uv": [ 2, 2.75, 3, 4 ], "texture": "#0" }
			}
		},
		{
			"__comment": "Element",
			"from": [ 7.5148, 3.8914, 12.671 ],
			"to": [ 8.664799, 5.0414, 23.021 ],
			"rotation": { "origin": [ 8.664791, 4.46643, 17.55854 ], "axis": "x", "angle": 45 },
			"faces": {
				"down": { "uv": [ 5, 8.5, 4.75, 9.75 ], "texture": "#0" },
				"up": { "uv": [ 4.75, 9.75, 4.5, 8.5 ], "texture": "#0" },
				"north": { "uv": [ 12, 10, 12.25, 10.25 ], "texture": "#0" },
				"south": { "uv": [ 12, 10.25, 12.25, 10.5 ], "texture": "#0" },
				"west": { "uv": [ 8.25, 4.5, 9.5, 4.75 ], "texture": "#0" },
				"east": { "uv": [ 8.25, 4.25, 9.5, 4.5 ], "texture": "#0" }
			}
		},
		{
			"__comment": "Element",
			"from": [ 7.2848, 6.4219, -11.5917 ],
			"to": [ 8.664801, 7.5719, 4.508301 ],
			"rotation": { "origin": [ 7.845416, 8.223043, 3.70734 ], "axis": "x", "angle": -45 },
			"faces": {
				"down": { "uv": [ 1, 7, 0.75, 8.75 ], "texture": "#0" },
				"up": { "uv": [ 0.75, 8.75, 0.5, 7 ], "texture": "#0" },
				"north": { "uv": [ 12, 10.5, 12.25, 10.75 ], "texture": "#0" },
				"south": { "uv": [ 12, 10.75, 12.25, 11 ], "texture": "#0" },
				"west": { "uv": [ 6.75, 2.75, 8.5, 3 ], "texture": "#0" },
				"east": { "uv": [ 6.75, 2.5, 8.5, 2.75 ], "texture": "#0" }
			}
		},
		{
			"__comment": "Element",
			"from": [ 7.7448, -11.6641, -4.5476 ],
			"to": [ 8.0898, -0.4516001, 2.2949 ],
			"rotation": { "origin": [ 8.089791, -1.429091, -3.39759 ], "axis": "x", "angle": -45 },
			"faces": {
				"down": { "uv": [ 9.75, 9.75, 9.5, 10.5 ], "texture": "#0" },
				"up": { "uv": [ 8.75, 10.5, 8.5, 9.75 ], "texture": "#0" },
				"north": { "uv": [ 5, 8.5, 5.25, 9.75 ], "texture": "#0" },
				"south": { "uv": [ 5.25, 8.5, 5.5, 9.75 ], "texture": "#0" },
				"west": { "uv": [ 4, 4, 4.75, 5.25 ], "texture": "#0" },
				"east": { "uv": [ 1.75, 4, 2.5, 5.25 ], "texture": "#0" }
			}
		},
		{
			"__comment": "Element",
			"from": [ 7.7448, -9.1916, 3.3191 ],
			"to": [ 8.0898, -6.0291, 6.0791 ],
			"rotation": { "origin": [ 8.089791, -1.429091, 0.09905437 ], "axis": "x", "angle": -45 },
			"faces": {
				"down": { "uv": [ 0.5, 12.25, 0.25, 12.5 ], "texture": "#0" },
				"up": { "uv": [ 0.25, 12.5, 0, 12.25 ], "texture": "#0" },
				"north": { "uv": [ 12, 11, 12.25, 11.25 ], "texture": "#0" },
				"south": { "uv": [ 12, 11.5, 12.25, 11.75 ], "texture": "#0" },
				"west": { "uv": [ 12, 11.75, 12.25, 12 ], "texture": "#0" },
				"east": { "uv": [ 12, 11.25, 12.25, 11.5 ], "texture": "#0" }
			}
		},
		{
			"__comment": "Element",
			"from": [ 7.8598, 2.0811, 17.1521 ],
			"to": [ 8.2048, 3.1736, 21.2346 ],
			"rotation": { "origin": [ 8.032291, 3.058577, 17.46831 ], "axis": "x", "angle": 22.5 },
			"faces": {
				"down": { "uv": [ 10.5, 6.5, 10.25, 7 ], "texture": "#0" },
				"up": { "uv": [ 10.5, 6.5, 10.25, 6 ], "texture": "#0" },
				"north": { "uv": [ 0.5, 12.25, 0.75, 12.5 ], "texture": "#0" },
				"south": { "uv": [ 0.75, 12.25, 1, 12.5 ], "texture": "#0" },
				"west": { "uv": [ 10.25, 5.5, 10.75, 5.75 ], "texture": "#0" },
				"east": { "uv": [ 10.25, 4.5, 10.75, 4.75 ], "texture": "#0" }
			}
		},
		{
			"__comment": "Element",
			"from": [ 7.8598, 3.2311, 17.1521 ],
			"to": [ 8.2048, 4.036098, 19.5096 ],
			"rotation": { "origin": [ 8.032291, 3.921077, 17.46831 ], "axis": "x", "angle": 22.5 },
			"faces": {
				"down": { "uv": [ 2.5, 12.25, 2.25, 12.5 ], "texture": "#0" },
				"up": { "uv": [ 2.25, 12.5, 2, 12.25 ], "texture": "#0" },
				"north": { "uv": [ 1, 12.25, 1.25, 12.5 ], "texture": "#0" },
				"south": { "uv": [ 1.5, 12.25, 1.75, 12.5 ], "texture": "#0" },
				"west": { "uv": [ 1.75, 12.25, 2, 12.5 ], "texture": "#0" },
				"east": { "uv": [ 1.25, 12.25, 1.5, 12.5 ], "texture": "#0" }
			}
		},
		{
			"__comment": "Element",
			"from": [ 7.8598, 1.2761, 14.3346 ],
			"to": [ 8.2048, 4.8986, 17.2096 ],
			"faces": {
				"down": { "uv": [ 3, 12.25, 2.75, 12.5 ], "texture": "#0" },
				"up": { "uv": [ 2.75, 12.5, 2.5, 12.25 ], "texture": "#0" },
				"north": { "uv": [ 10.25, 7, 10.5, 7.5 ], "texture": "#0" },
				"south": { "uv": [ 10.25, 8.5, 10.5, 9 ], "texture": "#0" },
				"west": { "uv": [ 10.25, 9, 10.5, 9.5 ], "texture": "#0" },
				"east": { "uv": [ 10.25, 8, 10.5, 8.5 ], "texture": "#0" }
			}
		},
		{
			"__comment": "Element",
			"from": [ 7.8598, 0.0686, 14.3346 ],
			"to": [ 8.2048, 1.2761, 15.9446 ],
			"faces": {
				"down": { "uv": [ 4.5, 12.25, 4.25, 12.5 ], "texture": "#0" },
				"up": { "uv": [ 4.25, 12.5, 4, 12.25 ], "texture": "#0" },
				"north": { "uv": [ 3, 12.25, 3.25, 12.5 ], "texture": "#0" },
				"south": { "uv": [ 3.5, 12.25, 3.75, 12.5 ], "texture": "#0" },
				"west": { "uv": [ 3.75, 12.25, 4, 12.5 ], "texture": "#0" },
				"east": { "uv": [ 3.25, 12.25, 3.5, 12.5 ], "texture": "#0" }
			}
		},
		{
			"__comment": "Element",
			"from": [ 7.8598, -1.9439, 14.9096 ],
			"to": [ 8.2048, -0.3339, 15.1971 ],
			"rotation": { "origin": [ 8.032291, -0.6214226, 14.73706 ], "axis": "x", "angle": 22.5 },
			"faces": {
				"down": { "uv": [ 6, 12.25, 5.75, 12.5 ], "texture": "#0" },
				"up": { "uv": [ 5.75, 12.5, 5.5, 12.25 ], "texture": "#0" },
				"north": { "uv": [ 4.5, 12.25, 4.75, 12.5 ], "texture": "#0" },
				"south": { "uv": [ 5, 12.25, 5.25, 12.5 ], "texture": "#0" },
				"west": { "uv": [ 5.25, 12.25, 5.5, 12.5 ], "texture": "#0" },
				"east": { "uv": [ 4.75, 12.25, 5, 12.5 ], "texture": "#0" }
			}
		},
		{
			"__comment": "Element",
			"from": [ 7.8598, -2.1739, 14.3346 ],
			"to": [ 8.2048, 0.3561001, 14.6796 ],
			"faces": {
				"down": { "uv": [ 7.5, 12.25, 7.25, 12.5 ], "texture": "#0" },
				"up": { "uv": [ 7.25, 12.5, 7, 12.25 ], "texture": "#0" },
				"north": { "uv": [ 6, 12.25, 6.25, 12.5 ], "texture": "#0" },
				"south": { "uv": [ 6.5, 12.25, 6.75, 12.5 ], "texture": "#0" },
				"west": { "uv": [ 6.75, 12.25, 7, 12.5 ], "texture": "#0" },
				"east": { "uv": [ 6.25, 12.25, 6.5, 12.5 ], "texture": "#0" }
			}
		},
		{
			"__comment": "Element",
			"from": [ 7.8598, -1.2539, 14.6221 ],
			"to": [ 8.2048, -0.2763997, 14.9671 ],
			"faces": {
				"down": { "uv": [ 9, 12.25, 8.75, 12.5 ], "texture": "#0" },
				"up": { "uv": [ 8.75, 12.5, 8.5, 12.25 ], "texture": "#0" },
				"north": { "uv": [ 7.5, 12.25, 7.75, 12.5 ], "texture": "#0" },
				"south": { "uv": [ 8, 12.25, 8.25, 12.5 ], "texture": "#0" },
				"west": { "uv": [ 8.25, 12.25, 8.5, 12.5 ], "texture": "#0" },
				"east": { "uv": [ 7.75, 12.25, 8, 12.5 ], "texture": "#0" }
			}
		},
		{
			"__comment": "Element",
			"from": [ 7.8598, -1.2539, 16.1746 ],
			"to": [ 8.2048, 2.5986, 17.3246 ],
			"rotation": { "origin": [ 8.032291, 1.621077, 16.83581 ], "axis": "x", "angle": 45 },
			"faces": {
				"down": { "uv": [ 9.5, 12.25, 9.25, 12.5 ], "texture": "#0" },
				"up": { "uv": [ 9.25, 12.5, 9, 12.25 ], "texture": "#0" },
				"north": { "uv": [ 1, 10.5, 1.25, 11 ], "texture": "#0" },
				"south": { "uv": [ 1.5, 10.5, 1.75, 11 ], "texture": "#0" },
				"west": { "uv": [ 1.75, 10.5, 2, 11 ], "texture": "#0" },
				"east": { "uv": [ 1.25, 10.5, 1.5, 11 ], "texture": "#0" }
			}
		},
		{
			"__comment": "Element",
			"from": [ 7.8598, 4.8986, 14.3346 ],
			"to": [ 8.2048, 5.9336, 16.3471 ],
			"faces": {
				"down": { "uv": [ 11, 12.25, 10.75, 12.5 ], "texture": "#0" },
				"up": { "uv": [ 10.75, 12.5, 10.5, 12.25 ], "texture": "#0" },
				"north": { "uv": [ 9.5, 12.25, 9.75, 12.5 ], "texture": "#0" },
				"south": { "uv": [ 10, 12.25, 10.25, 12.5 ], "texture": "#0" },
				"west": { "uv": [ 10.25, 12.25, 10.5, 12.5 ], "texture": "#0" },
				"east": { "uv": [ 9.75, 12.25, 10, 12.5 ], "texture": "#0" }
			}
		},
		{
			"__comment": "Element",
			"from": [ 7.8598, 5.9336, 14.3346 ],
			"to": [ 8.2048, 6.9686, 15.8296 ],
			"faces": {
				"down": { "uv": [ 12.5, 12.25, 12.25, 12.5 ], "texture": "#0" },
				"up": { "uv": [ 12.25, 12.5, 12, 12.25 ], "texture": "#0" },
				"north": { "uv": [ 11, 12.25, 11.25, 12.5 ], "texture": "#0" },
				"south": { "uv": [ 11.5, 12.25, 11.75, 12.5 ], "texture": "#0" },
				"west": { "uv": [ 11.75, 12.25, 12, 12.5 ], "texture": "#0" },
				"east": { "uv": [ 11.25, 12.25, 11.5, 12.5 ], "texture": "#0" }
			}
		},
		{
			"__comment": "Element",
			"from": [ 7.7448, -2.5791, 0.6849 ],
			"to": [ 8.0898, 4.1484, 5.4574 ],
			"faces": {
				"down": { "uv": [ 3, 10.5, 2.75, 11 ], "texture": "#0" },
				"up": { "uv": [ 2.75, 11, 2.5, 10.5 ], "texture": "#0" },
				"north": { "uv": [ 9.75, 9.75, 10, 10.5 ], "texture": "#0" },
				"south": { "uv": [ 9.75, 1.75, 10, 2.5 ], "texture": "#0" },
				"west": { "uv": [ 7.5, 8, 8, 8.75 ], "texture": "#0" },
				"east": { "uv": [ 7, 8, 7.5, 8.75 ], "texture": "#0" }
			}
		},
		{
			"__comment": "Element",
			"from": [ 7.7448, 4.0334, 3.7324 ],
			"to": [ 8.0898, 7.1384, 5.4574 ],
			"faces": {
				"down": { "uv": [ 12.5, 1.25, 12.25, 1.5 ], "texture": "#0" },
				"up": { "uv": [ 12.5, 1.25, 12.25, 1 ], "texture": "#0" },
				"north": { "uv": [ 12.25, 0, 12.5, 0.25 ], "texture": "#0" },
				"south": { "uv": [ 12.25, 0.5, 12.5, 0.75 ], "texture": "#0" },
				"west": { "uv": [ 12.25, 0.75, 12.5, 1 ], "texture": "#0" },
				"east": { "uv": [ 12.25, 0.25, 12.5, 0.5 ], "texture": "#0" }
			}
		},
		{
			"__comment": "Element",
			"from": [ 7.7448, 4.0334, 2.0649 ],
			"to": [ 8.0898, 5.7009, 3.9049 ],
			"faces": {
				"down": { "uv": [ 12.5, 2.75, 12.25, 3 ], "texture": "#0" },
				"up": { "uv": [ 12.5, 2.75, 12.25, 2.5 ], "texture": "#0" },
				"north": { "uv": [ 12.25, 1.5, 12.5, 1.75 ], "texture": "#0" },
				"south": { "uv": [ 12.25, 2, 12.5, 2.25 ], "texture": "#0" },
				"west": { "uv": [ 12.25, 2.25, 12.5, 2.5 ], "texture": "#0" },
				"east": { "uv": [ 12.25, 1.75, 12.5, 2 ], "texture": "#0" }
			}
		},
		{
			"__comment": "Element",
			"from": [ 7.8598, 9.502, 3.0615 ],
			"to": [ 8.1473, 10.2495, 3.349 ],
			"rotation": { "origin": [ 7.802291, 9.128162, 3.344446 ], "axis": "x", "angle": 22.5 },
			"faces": {
				"down": { "uv": [ 12.5, 4.25, 12.25, 4.5 ], "texture": "#0" },
				"up": { "uv": [ 12.5, 4.25, 12.25, 4 ], "texture": "#0" },
				"north": { "uv": [ 12.25, 3, 12.5, 3.25 ], "texture": "#0" },
				"south": { "uv": [ 12.25, 3.5, 12.5, 3.75 ], "texture": "#0" },
				"west": { "uv": [ 12.25, 3.75, 12.5, 4 ], "texture": "#0" },
				"east": { "uv": [ 12.25, 3.25, 12.5, 3.5 ], "texture": "#0" }
			}
		},
		{
			"__comment": "Element",
			"from": [ 7.5723, 8.1254, 3.3713 ],
			"to": [ 8.434799, 9.2754, 4.2338 ],
			"rotation": { "origin": [ 7.802291, 8.610662, 3.861946 ], "axis": "x", "angle": -22.5 },
			"faces": {
				"down": { "uv": [ 12.5, 5.75, 12.25, 6 ], "texture": "#0" },
				"up": { "uv": [ 12.5, 5.75, 12.25, 5.5 ], "texture": "#0" },
				"north": { "uv": [ 12.25, 4.5, 12.5, 4.75 ], "texture": "#0" },
				"south": { "uv": [ 12.25, 5, 12.5, 5.25 ], "texture": "#0" },
				"west": { "uv": [ 12.25, 5.25, 12.5, 5.5 ], "texture": "#0" },
				"east": { "uv": [ 12.25, 4.75, 12.5, 5 ], "texture": "#0" }
			}
		},
		{
			"__comment": "Element",
			"from": [ 7.3423, 7.8543, 4.0823 ],
			"to": [ 8.664801, 9.004301, 4.714797 ],
			"rotation": { "origin": [ 7.802291, 8.643299, 3.909303 ], "axis": "x", "angle": 45 },
			"faces": {
				"down": { "uv": [ 12.5, 7.25, 12.25, 7.5 ], "texture": "#0" },
				"up": { "uv": [ 12.5, 7.25, 12.25, 7 ], "texture": "#0" },
				"north": { "uv": [ 12.25, 6, 12.5, 6.25 ], "texture": "#0" },
				"south": { "uv": [ 12.25, 6.5, 12.5, 6.75 ], "texture": "#0" },
				"west": { "uv": [ 12.25, 6.75, 12.5, 7 ], "texture": "#0" },
				"east": { "uv": [ 12.25, 6.25, 12.5, 6.5 ], "texture": "#0" }
			}
		},
		{
			"__comment": "Element",
			"from": [ 7.5723, 4.7448, 4.4526 ],
			"to": [ 8.434799, 7.6198, 5.3151 ],
			"faces": {
				"down": { "uv": [ 12.5, 8.75, 12.25, 9 ], "texture": "#0" },
				"up": { "uv": [ 12.5, 8.75, 12.25, 8.5 ], "texture": "#0" },
				"north": { "uv": [ 12.25, 7.5, 12.5, 7.75 ], "texture": "#0" },
				"south": { "uv": [ 12.25, 8, 12.5, 8.25 ], "texture": "#0" },
				"west": { "uv": [ 12.25, 8.25, 12.5, 8.5 ], "texture": "#0" },
				"east": { "uv": [ 12.25, 7.75, 12.5, 8 ], "texture": "#0" }
			}
		},
		{
			"__comment": "Element",
			"from": [ 7.5723, 2.7192, 4.9699 ],
			"to": [ 8.434799, 5.0192, 5.832397 ],
			"rotation": { "origin": [ 8.003541, 3.581712, 5.401153 ], "axis": "x", "angle": -22.5 },
			"faces": {
				"down": { "uv": [ 12.5, 10.25, 12.25, 10.5 ], "texture": "#0" },
				"up": { "uv": [ 12.5, 10.25, 12.25, 10 ], "texture": "#0" },
				"north": { "uv": [ 12.25, 9, 12.5, 9.25 ], "texture": "#0" },
				"south": { "uv": [ 12.25, 9.5, 12.5, 9.75 ], "texture": "#0" },
				"west": { "uv": [ 12.25, 9.75, 12.5, 10 ], "texture": "#0" },
				"east": { "uv": [ 12.25, 9.25, 12.5, 9.5 ], "texture": "#0" }
			}
		},
		{
			"__comment": "Element",
			"from": [ 7.5723, -2.3976, 5.2671 ],
			"to": [ 8.434799, 2.9499, 6.1296 ],
			"faces": {
				"down": { "uv": [ 12.5, 10.75, 12.25, 11 ], "texture": "#0" },
				"up": { "uv": [ 12.5, 10.75, 12.25, 10.5 ], "texture": "#0" },
				"north": { "uv": [ 3.75, 10.5, 4, 11 ], "texture": "#0" },
				"south": { "uv": [ 4.25, 10.5, 4.5, 11 ], "texture": "#0" },
				"west": { "uv": [ 5, 10.5, 5.25, 11 ], "texture": "#0" },
				"east": { "uv": [ 4, 10.5, 4.25, 11 ], "texture": "#0" }
			}
		},
		{
			"__comment": "Element",
			"from": [ 7.5723, -10.9206, 4.7498 ],
			"to": [ 8.434799, -2.123099, 5.612298 ],
			"rotation": { "origin": [ 8.003541, -3.560639, 5.181088 ], "axis": "x", "angle": 22.5 },
			"faces": {
				"down": { "uv": [ 12.5, 11.25, 12.25, 11.5 ], "texture": "#0" },
				"up": { "uv": [ 12.5, 11.25, 12.25, 11 ], "texture": "#0" },
				"north": { "uv": [ 9.25, 4.75, 9.5, 5.75 ], "texture": "#0" },
				"south": { "uv": [ 1, 9.5, 1.25, 10.5 ], "texture": "#0" },
				"west": { "uv": [ 1.25, 9.5, 1.5, 10.5 ], "texture": "#0" },
				"east": { "uv": [ 9.25, 6.75, 9.5, 7.75 ], "texture": "#0" }
			}
		},
		{
			"__comment": "Element",
			"from": [ 7.3423, -9.6987, 1.8808 ],
			"to": [ 8.664801, -9.066199, 3.1458 ],
			"rotation": { "origin": [ 7.802291, -9.8717, 2.241803 ], "axis": "x", "angle": 22.5 },
			"faces": {
				"down": { "uv": [ 0.75, 12.5, 0.5, 12.75 ], "texture": "#0" },
				"up": { "uv": [ 0.5, 12.75, 0.25, 12.5 ], "texture": "#0" },
				"north": { "uv": [ 12.25, 11.5, 12.5, 11.75 ], "texture": "#0" },
				"south": { "uv": [ 12.25, 12, 12.5, 12.25 ], "texture": "#0" },
				"west": { "uv": [ 0, 12.5, 0.25, 12.75 ], "texture": "#0" },
				"east": { "uv": [ 12.25, 11.75, 12.5, 12 ], "texture": "#0" }
			}
		},
		{
			"__comment": "Element",
			"from": [ 7.6298, -10.7067, 2.016 ],
			"to": [ 8.377299, -10.1892, 2.476 ],
			"rotation": { "origin": [ 8.003541, -10.44797, 2.245989 ], "axis": "x", "angle": -45 },
			"faces": {
				"down": { "uv": [ 2.25, 12.5, 2, 12.75 ], "texture": "#0" },
				"up": { "uv": [ 2, 12.75, 1.75, 12.5 ], "texture": "#0" },
				"north": { "uv": [ 0.75, 12.5, 1, 12.75 ], "texture": "#0" },
				"south": { "uv": [ 1.25, 12.5, 1.5, 12.75 ], "texture": "#0" },
				"west": { "uv": [ 1.5, 12.5, 1.75, 12.75 ], "texture": "#0" },
				"east": { "uv": [ 1, 12.5, 1.25, 12.75 ], "texture": "#0" }
			}
		},
		{
			"__comment": "Element",
			"from": [ 7.8598, -10.8828, 1.4443 ],
			"to": [ 8.1473, -10.5953, 2.1918 ],
			"rotation": { "origin": [ 8.003541, -10.73905, 1.818051 ], "axis": "x", "angle": -22.5 },
			"faces": {
				"down": { "uv": [ 3.75, 12.5, 3.5, 12.75 ], "texture": "#0" },
				"up": { "uv": [ 3.5, 12.75, 3.25, 12.5 ], "texture": "#0" },
				"north": { "uv": [ 2.25, 12.5, 2.5, 12.75 ], "texture": "#0" },
				"south": { "uv": [ 2.75, 12.5, 3, 12.75 ], "texture": "#0" },
				"west": { "uv": [ 3, 12.5, 3.25, 12.75 ], "texture": "#0" },
				"east": { "uv": [ 2.5, 12.5, 2.75, 12.75 ], "texture": "#0" }
			}
		},
		{
			"__comment": "Element",
			"from": [ 7.5723, 5.1542, 4.313 ],
			"to": [ 8.434799, 6.0167, 9.487999 ],
			"rotation": { "origin": [ 8.003541, 5.585495, 9.2005 ], "axis": "x", "angle": 22.5 },
			"faces": {
				"down": { "uv": [ 5.75, 10.5, 5.5, 11 ], "texture": "#0" },
				"up": { "uv": [ 5.5, 11, 5.25, 10.5 ], "texture": "#0" },
				"north": { "uv": [ 3.75, 12.5, 4, 12.75 ], "texture": "#0" },
				"south": { "uv": [ 4, 12.5, 4.25, 12.75 ], "texture": "#0" },
				"west": { "uv": [ 10.25, 9.5, 10.75, 9.75 ], "texture": "#0" },
				"east": { "uv": [ 10.25, 7.5, 10.75, 7.75 ], "texture": "#0" }
			}
		},
		{
			"__comment": "Element",
			"from": [ 7.5723, 3.1048, 8.484099 ],
			"to": [ 8.434799, 3.9673, 12.7966 ],
			"rotation": { "origin": [ 8.003541, 3.536034, 11.35914 ], "axis": "x", "angle": 45 },
			"faces": {
				"down": { "uv": [ 7.25, 10.5, 7, 11 ], "texture": "#0" },
				"up": { "uv": [ 7, 11, 6.75, 10.5 ], "texture": "#0" },
				"north": { "uv": [ 4.25, 12.5, 4.5, 12.75 ], "texture": "#0" },
				"south": { "uv": [ 4.5, 12.5, 4.75, 12.75 ], "texture": "#0" },
				"west": { "uv": [ 6.25, 10.5, 6.75, 10.75 ], "texture": "#0" },
				"east": { "uv": [ 10.25, 10, 10.75, 10.25 ], "texture": "#0" }
			}
		},
		{
			"__comment": "Element",
			"from": [ 7.5723, -3.2589, 13.0281 ],
			"to": [ 8.434799, 2.8936, 13.8906 ],
			"rotation": { "origin": [ 8.003541, -0.1826056, 13.45934 ], "axis": "x", "angle": -22.5 },
			"faces": {
				"down": { "uv": [ 5.25, 12.5, 5, 12.75 ], "texture": "#0" },
				"up": { "uv": [ 5, 12.75, 4.75, 12.5 ], "texture": "#0" },
				"north": { "uv": [ 9.75, 2.5, 10, 3.25 ], "texture": "#0" },
				"south": { "uv": [ 9.75, 4.25, 10, 5 ], "texture": "#0" },
				"west": { "uv": [ 9.75, 5.75, 10, 6.5 ], "texture": "#0" },
				"east": { "uv": [ 9.75, 3.5, 10, 4.25 ], "texture": "#0" }
			}
		},
		{
			"__comment": "Element",
			"from": [ 7.3423, -3.7927, 14.0288 ],
			"to": [ 8.664801, -2.6427, 14.6613 ],
			"rotation": { "origin": [ 7.802291, -3.431701, 14.8343 ], "axis": "x", "angle": 45 },
			"faces": {
				"down": { "uv": [ 6.75, 12.5, 6.5, 12.75 ], "texture": "#0" },
				"up": { "uv": [ 6.5, 12.75, 6.25, 12.5 ], "texture": "#0" },
				"north": { "uv": [ 5.25, 12.5, 5.5, 12.75 ], "texture": "#0" },
				"south": { "uv": [ 5.75, 12.5, 6, 12.75 ], "texture": "#0" },
				"west": { "uv": [ 6, 12.5, 6.25, 12.75 ], "texture": "#0" },
				"east": { "uv": [ 5.5, 12.5, 5.75, 12.75 ], "texture": "#0" }
			}
		},
		{
			"__comment": "Element",
			"from": [ 7.5723, -4.0638, 14.5098 ],
			"to": [ 8.434799, -2.9138, 15.3723 ],
			"rotation": { "origin": [ 7.802291, -3.399064, 14.88166 ], "axis": "x", "angle": -22.5 },
			"faces": {
				"down": { "uv": [ 8.25, 12.5, 8, 12.75 ], "texture": "#0" },
				"up": { "uv": [ 8, 12.75, 7.75, 12.5 ], "texture": "#0" },
				"north": { "uv": [ 6.75, 12.5, 7, 12.75 ], "texture": "#0" },
				"south": { "uv": [ 7.25, 12.5, 7.5, 12.75 ], "texture": "#0" },
				"west": { "uv": [ 7.5, 12.5, 7.75, 12.75 ], "texture": "#0" },
				"east": { "uv": [ 7, 12.5, 7.25, 12.75 ], "texture": "#0" }
			}
		},
		{
			"__comment": "Element",
			"from": [ 7.6298, -4.5238, 14.8548 ],
			"to": [ 8.377299, -4.0638, 15.3723 ],
			"rotation": { "origin": [ 7.802291, -3.859064, 14.88166 ], "axis": "x", "angle": -22.5 },
			"faces": {
				"down": { "uv": [ 9.75, 12.5, 9.5, 12.75 ], "texture": "#0" },
				"up": { "uv": [ 9.5, 12.75, 9.25, 12.5 ], "texture": "#0" },
				"north": { "uv": [ 8.25, 12.5, 8.5, 12.75 ], "texture": "#0" },
				"south": { "uv": [ 8.75, 12.5, 9, 12.75 ], "texture": "#0" },
				"west": { "uv": [ 9, 12.5, 9.25, 12.75 ], "texture": "#0" },
				"east": { "uv": [ 8.5, 12.5, 8.75, 12.75 ], "texture": "#0" }
			}
		},
		{
			"__comment": "Element",
			"from": [ 7.8598, -4.9804, 15.3371 ],
			"to": [ 8.1473, -4.2329, 15.6246 ],
			"rotation": { "origin": [ 7.802291, -3.859064, 15.34166 ], "axis": "x", "angle": 22.5 },
			"faces": {
				"down": { "uv": [ 11.25, 12.5, 11, 12.75 ], "texture": "#0" },
				"up": { "uv": [ 11, 12.75, 10.75, 12.5 ], "texture": "#0" },
				"north": { "uv": [ 9.75, 12.5, 10, 12.75 ], "texture": "#0" },
				"south": { "uv": [ 10.25, 12.5, 10.5, 12.75 ], "texture": "#0" },
				"west": { "uv": [ 10.5, 12.5, 10.75, 12.75 ], "texture": "#0" },
				"east": { "uv": [ 10, 12.5, 10.25, 12.75 ], "texture": "#0" }
			}
		},
		{
			"__comment": "Element",
			"from": [ 7.6298, -0.3263, 21.0648 ],
			"to": [ 8.4923, 0.8237, 21.9273 ],
			"rotation": { "origin": [ 7.859791, 0.3384364, 21.43666 ], "axis": "x", "angle": -22.5 },
			"faces": {
				"down": { "uv": [ 12.75, 12.5, 12.5, 12.75 ], "texture": "#0" },
				"up": { "uv": [ 12.5, 12.75, 12.25, 12.5 ], "texture": "#0" },
				"north": { "uv": [ 11.25, 12.5, 11.5, 12.75 ], "texture": "#0" },
				"south": { "uv": [ 11.75, 12.5, 12, 12.75 ], "texture": "#0" },
				"west": { "uv": [ 12, 12.5, 12.25, 12.75 ], "texture": "#0" },
				"east": { "uv": [ 11.5, 12.5, 11.75, 12.75 ], "texture": "#0" }
			}
		},
		{
			"__comment": "Element",
			"from": [ 7.6873, -0.7863, 21.4098 ],
			"to": [ 8.434799, -0.3263, 21.9273 ],
			"rotation": { "origin": [ 7.859791, -0.1215636, 21.43666 ], "axis": "x", "angle": -22.5 },
			"faces": {
				"down": { "uv": [ 12.75, 1.25, 12.5, 1.5 ], "texture": "#0" },
				"up": { "uv": [ 12.75, 1.25, 12.5, 1 ], "texture": "#0" },
				"north": { "uv": [ 12.5, 0, 12.75, 0.25 ], "texture": "#0" },
				"south": { "uv": [ 12.5, 0.5, 12.75, 0.75 ], "texture": "#0" },
				"west": { "uv": [ 12.5, 0.75, 12.75, 1 ], "texture": "#0" },
				"east": { "uv": [ 12.5, 0.25, 12.75, 0.5 ], "texture": "#0" }
			}
		},
		{
			"__comment": "Element",
			"from": [ 7.8598, -1.0704, 21.6046 ],
			"to": [ 8.2623, -0.6679, 21.8921 ],
			"rotation": { "origin": [ 7.859791, -0.2940636, 21.60916 ], "axis": "x", "angle": -22.5 },
			"faces": {
				"down": { "uv": [ 12.75, 2.75, 12.5, 3 ], "texture": "#0" },
				"up": { "uv": [ 12.75, 2.75, 12.5, 2.5 ], "texture": "#0" },
				"north": { "uv": [ 12.5, 1.5, 12.75, 1.75 ], "texture": "#0" },
				"south": { "uv": [ 12.5, 2, 12.75, 2.25 ], "texture": "#0" },
				"west": { "uv": [ 12.5, 2.25, 12.75, 2.5 ], "texture": "#0" },
				"east": { "uv": [ 12.5, 1.75, 12.75, 2 ], "texture": "#0" }
			}
		},
		{
			"__comment": "Element",
			"from": [ 7.9173, -1.4202, 21.9376 ],
			"to": [ 8.2048, -0.9027, 22.1101 ],
			"faces": {
				"down": { "uv": [ 12.75, 4.25, 12.5, 4.5 ], "texture": "#0" },
				"up": { "uv": [ 12.75, 4.25, 12.5, 4 ], "texture": "#0" },
				"north": { "uv": [ 12.5, 3, 12.75, 3.25 ], "texture": "#0" },
				"south": { "uv": [ 12.5, 3.5, 12.75, 3.75 ], "texture": "#0" },
				"west": { "uv": [ 12.5, 3.75, 12.75, 4 ], "texture": "#0" },
				"east": { "uv": [ 12.5, 3.25, 12.75, 3.5 ], "texture": "#0" }
			}
		},
		{
			"__comment": "Element",
			"from": [ 7.6298, 9.2754, 3.3713 ],
			"to": [ 8.377299, 9.7354, 3.8888 ],
			"rotation": { "origin": [ 7.802291, 9.070662, 3.861946 ], "axis": "x", "angle": -22.5 },
			"faces": {
				"down": { "uv": [ 12.75, 5.75, 12.5, 6 ], "texture": "#0" },
				"up": { "uv": [ 12.75, 5.75, 12.5, 5.5 ], "texture": "#0" },
				"north": { "uv": [ 12.5, 4.5, 12.75, 4.75 ], "texture": "#0" },
				"south": { "uv": [ 12.5, 5, 12.75, 5.25 ], "texture": "#0" },
				"west": { "uv": [ 12.5, 5.25, 12.75, 5.5 ], "texture": "#0" },
				"east": { "uv": [ 12.5, 4.75, 12.75, 5 ], "texture": "#0" }
			}
		}
	],
	"display": {
		"thirdperson_righthand": {
			"rotation":  [ 90, 35, 0 ],
			"translation":  [ 12.848, -20.09, 24.188 ],
			"scale":  [ 1.0054, 1.0054, 1.0054 ]
		},
		"thirdperson_lefthand": {
			"rotation":  [ 90, 35, 0 ],
			"translation":  [ 12.848, -20.09, 24.188 ],
			"scale":  [ 1.0054, 1.0054, 1.0054 ]
		},
		"gui": {
			"rotation":  [ 25, 135, 0 ],
			"scale":  [ 0.6956522, 0.6956522, 0.6956522 ]
		},
		"head": {
			"rotation":  [ 0, -35, 0 ],
			"translation":  [ -19.75, 22.701, 29.755 ],
			"scale":  [ 1.6086, 1.6086, 1.6086 ]
		}
	}
}