{
  "textures": {
    "0": "minescape/entities/airborne-kalphite",
    "particle": "minescape/entities/airborne-kalphite"
  },
  "elements": [
    {
      "from": [
        -4.9461341999999995,
        -3.524085299999996,
        5.938625000000001
      ],
      "to": [
        -2.962384199999999,
        -2.661585299999995,
        7.318625
      ],
      "rotation": {
        "angle": 22.5,
        "axis": "z",
        "origin": [
          3.2907407999999982,
          -3.0928352999999973,
          8.396749999999999
        ]
      },
      "faces": {
        "north": {
          "uv": [
            10,
            5.75,
            10.25,
            6
          ],
          "texture": "#0"
        },
        "east": {
          "uv": [
            10,
            6,
            10.25,
            6.25
          ],
          "texture": "#0"
        },
        "south": {
          "uv": [
            10,
            6.25,
            10.25,
            6.5
          ],
          "texture": "#0"
        },
        "west": {
          "uv": [
            10,
            6.5,
            10.25,
            6.75
          ],
          "texture": "#0"
        },
        "up": {
          "uv": [
            10.25,
            7,
            10,
            6.75
          ],
          "texture": "#0"
        },
        "down": {
          "uv": [
            10.25,
            7,
            10,
            7.25
          ],
          "texture": "#0"
        }
      }
    },
    {
      "from": [
        -4.083634199999999,
        -3.524085299999996,
        7.318625
      ],
      "to": [
        -2.962384199999999,
        -2.661585299999995,
        10.768625000000002
      ],
      "rotation": {
        "angle": 22.5,
        "axis": "z",
        "origin": [
          3.2907407999999982,
          -3.0928352999999973,
          8.396749999999999
        ]
      },
      "faces": {
        "north": {
          "uv": [
            10,
            7.25,
            10.25,
            7.5
          ],
          "texture": "#0"
        },
        "east": {
          "uv": [
            10,
            7.5,
            10.25,
            7.75
          ],
          "texture": "#0"
        },
        "south": {
          "uv": [
            10,
            7.75,
            10.25,
            8
          ],
          "texture": "#0"
        },
        "west": {
          "uv": [
            10,
            8,
            10.25,
            8.25
          ],
          "texture": "#0"
        },
        "up": {
          "uv": [
            10.25,
            8.5,
            10,
            8.25
          ],
          "texture": "#0"
        },
        "down": {
          "uv": [
            10.25,
            8.5,
            10,
            8.75
          ],
          "texture": "#0"
        }
      }
    },
    {
      "from": [
        -2.962384199999999,
        -3.524085299999996,
        5.593625
      ],
      "to": [
        15.5813888,
        -2.661585299999995,
        11.199875000000002
      ],
      "rotation": {
        "angle": 22.5,
        "axis": "z",
        "origin": [
          3.2907407999999982,
          -3.0928352999999973,
          8.396749999999999
        ]
      },
      "faces": {
        "north": {
          "uv": [
            6.25,
            3.5,
            7.5,
            3.75
          ],
          "texture": "#0"
        },
        "east": {
          "uv": [
            3.25,
            8.5,
            3.75,
            8.75
          ],
          "texture": "#0"
        },
        "south": {
          "uv": [
            6.25,
            3.75,
            7.5,
            4
          ],
          "texture": "#0"
        },
        "west": {
          "uv": [
            3.75,
            8.5,
            4.25,
            8.75
          ],
          "texture": "#0"
        },
        "up": {
          "uv": [
            1.25,
            4.5,
            0,
            4
          ],
          "texture": "#0"
        },
        "down": {
          "uv": [
            2.5,
            4,
            1.25,
            4.5
          ],
          "texture": "#0"
        }
      }
    },
    {
      "from": [
        14.373865799999999,
        -3.524085299999996,
        6.456125
      ],
      "to": [
        23.3438888,
        -2.834108299999997,
        9.474875
      ],
      "rotation": {
        "angle": 22.5,
        "axis": "z",
        "origin": [
          3.2907407999999982,
          -3.0928352999999973,
          8.396749999999999
        ]
      },
      "faces": {
        "north": {
          "uv": [
            3.5,
            7.75,
            4.25,
            8
          ],
          "texture": "#0"
        },
        "east": {
          "uv": [
            10,
            8.75,
            10.25,
            9
          ],
          "texture": "#0"
        },
        "south": {
          "uv": [
            4.25,
            7.75,
            5,
            8
          ],
          "texture": "#0"
        },
        "west": {
          "uv": [
            10,
            9,
            10.25,
            9.25
          ],
          "texture": "#0"
        },
        "up": {
          "uv": [
            5.75,
            8,
            5,
            7.75
          ],
          "texture": "#0"
        },
        "down": {
          "uv": [
            6.5,
            7.75,
            5.75,
            8
          ],
          "texture": "#0"
        }
      }
    }
  ],
  "name": "wing3",
  "display": {
    "head": {
      "translation": [
        -57.2355552,
        -17.83041079999998,
        0.13799999999999812
      ],
      "scale": [
        4,
        4,
        4
      ]
    },
    "thirdperson_righthand": {
      "translation": [
        -35.772222,
        -2.086249999999999,
        -1.1440067499999884
      ],
      "rotation": [
        90,
        0,
        0
      ],
      "scale": [
        2.5,
        2.5,
        2.5
      ]
    },
    "thirdperson_lefthand": {
      "translation": [
        35.772222,
        -2.086249999999999,
        -1.1440067499999884
      ],
      "rotation": [
        90,
        0,
        0
      ],
      "scale": [
        2.5,
        2.5,
        2.5
      ]
    },
    "gui": {
      "rotation": [
        25,
        135,
        0
      ],
      "scale": [
        0.6956521739130436,
        0.6956521739130436,
        0.6956521739130436
      ]
    }
  }
}