{
  "textures": {
    "0": "minescape/entities/ice-fiend-boss",
    "particle": "minescape/entities/ice-fiend-boss"
  },
  "elements": [
    {
      "from": [
        7.5612625000000016,
        -1.7695187500000014,
        6.04965625
      ],
      "to": [
        8.3172625,
        -1.0855187500000003,
        6.76965625
      ],
      "rotation": {
        "angle": 45,
        "axis": "x",
        "origin": [
          5.661182500000001,
          0.07348124999999861,
          8.14707625
        ]
      },
      "faces": {
        "north": {
          "uv": [
            1.5,
            6.5,
            2,
            7
          ],
          "texture": "#0"
        },
        "east": {
          "uv": [
            2,
            6.5,
            2.5,
            7
          ],
          "texture": "#0"
        },
        "south": {
          "uv": [
            2.5,
            6.5,
            3,
            7
          ],
          "texture": "#0"
        },
        "west": {
          "uv": [
            3,
            6.5,
            3.5,
            7
          ],
          "texture": "#0"
        },
        "up": {
          "uv": [
            4,
            7,
            3.5,
            6.5
          ],
          "texture": "#0"
        },
        "down": {
          "uv": [
            4.5,
            6.5,
            4,
            7
          ],
          "texture": "#0"
        }
      }
    },
    {
      "from": [
        7.6692625,
        -1.1353687500000014,
        6.15543625
      ],
      "to": [
        8.2452625,
        -0.34336875000000155,
        8.315436250000001
      ],
      "rotation": {
        "angle": 22.5,
        "axis": "x",
        "origin": [
          5.661182500000001,
          0.07348124999999861,
          8.14707625
        ]
      },
      "faces": {
        "north": {
          "uv": [
            4.5,
            6.5,
            5,
            7
          ],
          "texture": "#0"
        },
        "east": {
          "uv": [
            3.5,
            0.5,
            4.5,
            1
          ],
          "texture": "#0"
        },
        "south": {
          "uv": [
            5,
            6.5,
            5.5,
            7
          ],
          "texture": "#0"
        },
        "west": {
          "uv": [
            3.5,
            1.5,
            4.5,
            2
          ],
          "texture": "#0"
        },
        "up": {
          "uv": [
            0.5,
            5,
            0,
            4
          ],
          "texture": "#0"
        },
        "down": {
          "uv": [
            1,
            4,
            0.5,
            5
          ],
          "texture": "#0"
        }
      }
    },
    {
      "from": [
        7.597262500000001,
        -1.1166887500000016,
        7.64063625
      ],
      "to": [
        8.4612625,
        0.6833112499999991,
        8.43263625
      ],
      "rotation": {
        "angle": 45,
        "axis": "x",
        "origin": [
          5.661182500000001,
          0.07348124999999861,
          8.14707625
        ]
      },
      "faces": {
        "north": {
          "uv": [
            5.5,
            6.5,
            6,
            7
          ],
          "texture": "#0"
        },
        "east": {
          "uv": [
            6,
            6.5,
            6.5,
            7
          ],
          "texture": "#0"
        },
        "south": {
          "uv": [
            6.5,
            6.5,
            7,
            7
          ],
          "texture": "#0"
        },
        "west": {
          "uv": [
            6.5,
            0,
            7,
            0.5
          ],
          "texture": "#0"
        },
        "up": {
          "uv": [
            7,
            1,
            6.5,
            0.5
          ],
          "texture": "#0"
        },
        "down": {
          "uv": [
            7,
            1,
            6.5,
            1.5
          ],
          "texture": "#0"
        }
      }
    },
    {
      "from": [
        7.5252625,
        0.6833112499999991,
        7.49663625
      ],
      "to": [
        8.677262500000001,
        3.2033112499999987,
        8.57663625
      ],
      "rotation": {
        "angle": 45,
        "axis": "x",
        "origin": [
          5.661182500000001,
          0.07348124999999861,
          8.14707625
        ]
      },
      "faces": {
        "north": {
          "uv": [
            1,
            4,
            1.5,
            5
          ],
          "texture": "#0"
        },
        "east": {
          "uv": [
            1.5,
            4,
            2,
            5
          ],
          "texture": "#0"
        },
        "south": {
          "uv": [
            2,
            4,
            2.5,
            5
          ],
          "texture": "#0"
        },
        "west": {
          "uv": [
            4,
            4,
            4.5,
            5
          ],
          "texture": "#0"
        },
        "up": {
          "uv": [
            7,
            2,
            6.5,
            1.5
          ],
          "texture": "#0"
        },
        "down": {
          "uv": [
            7,
            2,
            6.5,
            2.5
          ],
          "texture": "#0"
        }
      }
    },
    {
      "from": [
        7.885262500000001,
        -0.8473687500000011,
        8.89143625
      ],
      "to": [
        8.029262500000002,
        -0.63136875,
        9.17943625
      ],
      "rotation": {
        "angle": 22.5,
        "axis": "x",
        "origin": [
          5.661182500000001,
          0.07348124999999861,
          8.14707625
        ]
      },
      "faces": {
        "north": {
          "uv": [
            2,
            7,
            2.5,
            7.5
          ],
          "texture": "#0"
        },
        "east": {
          "uv": [
            2.5,
            7,
            3,
            7.5
          ],
          "texture": "#0"
        },
        "south": {
          "uv": [
            3,
            7,
            3.5,
            7.5
          ],
          "texture": "#0"
        },
        "west": {
          "uv": [
            3.5,
            7,
            4,
            7.5
          ],
          "texture": "#0"
        },
        "up": {
          "uv": [
            4.5,
            7.5,
            4,
            7
          ],
          "texture": "#0"
        },
        "down": {
          "uv": [
            5,
            7,
            4.5,
            7.5
          ],
          "texture": "#0"
        }
      }
    },
    {
      "from": [
        7.8132625,
        -0.9913687500000012,
        8.315436250000001
      ],
      "to": [
        8.1012625,
        -0.4873687500000017,
        8.603436250000001
      ],
      "rotation": {
        "angle": 22.5,
        "axis": "x",
        "origin": [
          5.661182500000001,
          0.07348124999999861,
          8.14707625
        ]
      },
      "faces": {
        "north": {
          "uv": [
            6.5,
            2.5,
            7,
            3
          ],
          "texture": "#0"
        },
        "east": {
          "uv": [
            6.5,
            3,
            7,
            3.5
          ],
          "texture": "#0"
        },
        "south": {
          "uv": [
            6.5,
            3.5,
            7,
            4
          ],
          "texture": "#0"
        },
        "west": {
          "uv": [
            6.5,
            4,
            7,
            4.5
          ],
          "texture": "#0"
        },
        "up": {
          "uv": [
            7,
            5,
            6.5,
            4.5
          ],
          "texture": "#0"
        },
        "down": {
          "uv": [
            7,
            5,
            6.5,
            5.5
          ],
          "texture": "#0"
        }
      }
    },
    {
      "from": [
        7.8492625,
        -0.9193687500000003,
        8.60343625
      ],
      "to": [
        8.065262500000001,
        -0.5593687500000009,
        8.89143625
      ],
      "rotation": {
        "angle": 22.5,
        "axis": "x",
        "origin": [
          5.661182500000001,
          0.07348124999999861,
          8.14707625
        ]
      },
      "faces": {
        "north": {
          "uv": [
            6.5,
            5.5,
            7,
            6
          ],
          "texture": "#0"
        },
        "east": {
          "uv": [
            6.5,
            6,
            7,
            6.5
          ],
          "texture": "#0"
        },
        "south": {
          "uv": [
            0,
            7,
            0.5,
            7.5
          ],
          "texture": "#0"
        },
        "west": {
          "uv": [
            0.5,
            7,
            1,
            7.5
          ],
          "texture": "#0"
        },
        "up": {
          "uv": [
            1.5,
            7.5,
            1,
            7
          ],
          "texture": "#0"
        },
        "down": {
          "uv": [
            2,
            7,
            1.5,
            7.5
          ],
          "texture": "#0"
        }
      }
    }
  ],
  "name": "arm4",
  "display": {
    "head": {
      "translation": [
        -0.40465000000000373,
        21.366515000000007,
        -0.15730500000000092
      ],
      "scale": [
        4,
        4,
        4
      ]
    },
    "thirdperson_righthand": {
      "translation": [
        -0.15283125000000197,
        -1.9016843749999994,
        23.354071875000002
      ],
      "rotation": [
        90,
        0,
        0
      ],
      "scale": [
        2.5,
        2.5,
        2.5
      ]
    },
    "thirdperson_lefthand": {
      "translation": [
        0.3529812500000027,
        -1.9016843749999994,
        23.354071875000002
      ],
      "rotation": [
        90,
        0,
        0
      ],
      "scale": [
        2.5,
        2.5,
        2.5
      ]
    },
    "gui": {
      "rotation": [
        25,
        135,
        0
      ],
      "scale": [
        1.6,
        1.6,
        1.6
      ]
    }
  }
}